st_batch_menu_group/__init__.py
st_batch_menu_group/frontend/build/asset-manifest.json
st_batch_menu_group/frontend/build/bootstrap.min.css
st_batch_menu_group/frontend/build/index.html
st_batch_menu_group/frontend/build/precache-manifest.a8929da9856285076b29fe0b485cead7.js
st_batch_menu_group/frontend/build/service-worker.js
st_batch_menu_group/frontend/build/static/js/2.ca59b467.chunk.js
st_batch_menu_group/frontend/build/static/js/2.ca59b467.chunk.js.LICENSE.txt
st_batch_menu_group/frontend/build/static/js/2.ca59b467.chunk.js.map
st_batch_menu_group/frontend/build/static/js/main.15b2685f.chunk.js
st_batch_menu_group/frontend/build/static/js/main.15b2685f.chunk.js.map
st_batch_menu_group/frontend/build/static/js/runtime-main.bc0103cb.js
st_batch_menu_group/frontend/build/static/js/runtime-main.bc0103cb.js.map
st_batch_menu_group-0.1.2.dist-info/licenses/LICENSE
st_batch_menu_group-0.1.2.dist-info/METADATA
st_batch_menu_group-0.1.2.dist-info/WHEEL
st_batch_menu_group-0.1.2.dist-info/top_level.txt
st_batch_menu_group-0.1.2.dist-info/RECORD
