Metadata-Version: 2.4
Name: st_batch_menu_group
Version: 0.1.2
Summary: Streamlit Component for a batch menu group
Home-page: https://github.com/locupleto/st_batch_menu_group
Author: Urban Ottosson
Author-email: urban@ottosson.org
Requires-Python: >=3.6
License-File: LICENSE
Requires-Dist: streamlit>=0.63
Dynamic: author
Dynamic: author-email
Dynamic: description
Dynamic: description-content-type
Dynamic: home-page
Dynamic: license-file
Dynamic: requires-dist
Dynamic: requires-python
Dynamic: summary
